flowclient/__init__.py
flowclient/_version.py
flowclient/aggregates.py
flowclient/api_query.py
flowclient/async_api_query.py
flowclient/async_client.py
flowclient/async_connection.py
flowclient/client.py
flowclient/connection.py
flowclient/errors.py
flowclient/query_specs.py
flowclient-1.34.0.dist-info/licenses/LICENSE
flowclient-1.34.0.dist-info/METADATA
flowclient-1.34.0.dist-info/WHEEL
flowclient-1.34.0.dist-info/top_level.txt
flowclient-1.34.0.dist-info/RECORD
